Metadata-Version: 2.1
Name: in-memory-table
Version: 1.0.0
Summary: In memory indexed data
Author-email: Sebastian Jordan <sebastian.jordan.mail@googlemail.com>
License: GPL-3.0-or-later
Classifier: Programming Language :: Python :: 3
Classifier: License :: OSI Approved :: GNU General Public License v3 or later (GPLv3+)
License-File: LICENSE
